scrapbox/__init__.py
scrapbox/client.py
scrapbox/main.py
scrapbox/models.py
scrapbox/py.typed
scrapbox_client-0.1.3.dist-info/METADATA
scrapbox_client-0.1.3.dist-info/WHEEL
scrapbox_client-0.1.3.dist-info/entry_points.txt
scrapbox_client-0.1.3.dist-info/licenses/LICENSE
scrapbox_client-0.1.3.dist-info/RECORD
