Metadata-Version: 2.4
Name: scrapbox-client
Version: 0.1.3
Summary: Scrapbox (Helpfeel Cosense) API Client
Project-URL: Repository, https://github.com/eggplants/scrapbox-client
Author-email: eggplants <w10776e8w@yahoo.co.jp>
License-File: LICENSE
Keywords: api,cli,client,cosense,helpfeel,scrapbox
Classifier: Development Status :: 4 - Beta
Classifier: Environment :: Console
Classifier: Intended Audience :: Developers
Classifier: License :: OSI Approved :: MIT License
Classifier: Operating System :: OS Independent
Classifier: Programming Language :: Python :: 3 :: Only
Classifier: Programming Language :: Python :: 3.14
Classifier: Topic :: Internet :: WWW/HTTP
Classifier: Topic :: Software Development :: Libraries :: Python Modules
Classifier: Topic :: Utilities
Classifier: Typing :: Typed
Requires-Python: >=3.14
Requires-Dist: httpx>=0.28.1
Requires-Dist: pydantic>=2.12.5
